{
  "rules": [
    {
      "match": {
        "blocks": {
          "blocks": [
            "minecraft:wheat:7"
          ] 
        },
        "harvester": {
          "heldItemMainHand": {
            "items": [
              "atherys:hoe_t3:*"
            ]
          }
        }
      },
      "replaceStrategy": "REPLACE_ALL_IF_SELECTED",
      "dropStrategy": "REPEAT",
      "dropCount": {
        "min": 0,
        "max": 2
      },
      "drops": [
        {
          "force": true,
          "item": {
            "items" : [
              "minecraft:wheat"
            ]
          }
        },
        {
          "force": true,
          "item": {
            "items" : [
              "minecraft:wheat_seeds:0#{display:{Name:\"§r§fWheat Seeds\"}}"
            ]
          }
        },
        {
          "selector": {
            "weight": {
              "value": 800
            }
          },
          "item": {
            "items" : [
              "minecraft:wheat_seeds:0#{display:{Name:\"§r§fWheat Seeds\"}}"
            ]
          }
        },
        {
          "selector": {
            "weight": {
              "value": 200
            }
          },
          "item": {
            "items" : [
              "minecraft:wheat_seeds:0#{display:{Name:\"§r§fWheat Seeds\"}}"
            ]
          }
        }
      ]
    }
  ]
}